hiba_regression/Linear_regression.py
hiba_regression/__init__.py
hiba_simple_linear_regression-0.1.dist-info/licenses/LICENSE.txt
hiba_simple_linear_regression-0.1.dist-info/METADATA
hiba_simple_linear_regression-0.1.dist-info/WHEEL
hiba_simple_linear_regression-0.1.dist-info/top_level.txt
hiba_simple_linear_regression-0.1.dist-info/RECORD
